odoo/addons/l10n_it_riba_sale_commission/README.rst
odoo/addons/l10n_it_riba_sale_commission/__init__.py
odoo/addons/l10n_it_riba_sale_commission/__manifest__.py
odoo/addons/l10n_it_riba_sale_commission/i18n/it.po
odoo/addons/l10n_it_riba_sale_commission/i18n/l10n_it_riba_sale_commission.pot
odoo/addons/l10n_it_riba_sale_commission/models/__init__.py
odoo/addons/l10n_it_riba_sale_commission/models/account_move.py
odoo/addons/l10n_it_riba_sale_commission/models/riba_config.py
odoo/addons/l10n_it_riba_sale_commission/readme/CONTRIBUTORS.rst
odoo/addons/l10n_it_riba_sale_commission/readme/DESCRIPTION.rst
odoo/addons/l10n_it_riba_sale_commission/static/description/icon.png
odoo/addons/l10n_it_riba_sale_commission/static/description/index.html
odoo/addons/l10n_it_riba_sale_commission/tests/__init__.py
odoo/addons/l10n_it_riba_sale_commission/tests/test_riba_sale_commission.py
odoo/addons/l10n_it_riba_sale_commission/views/configuration_riba_view.xml
odoo/addons/l10n_it_riba_sale_commission/views/invoice_no_commission.xml
odoo/addons/l10n_it_riba_sale_commission/wizard/__init__.py
odoo/addons/l10n_it_riba_sale_commission/wizard/wizard_riba_commissions_settle.py
odoo14_addon_l10n_it_riba_sale_commission-14.0.1.1.2.dist-info/METADATA
odoo14_addon_l10n_it_riba_sale_commission-14.0.1.1.2.dist-info/WHEEL
odoo14_addon_l10n_it_riba_sale_commission-14.0.1.1.2.dist-info/top_level.txt
odoo14_addon_l10n_it_riba_sale_commission-14.0.1.1.2.dist-info/RECORD
