Metadata-Version: 2.1
Name: odoo14-addon-l10n_it_riba_sale_commission
Version: 14.0.1.1.2
Summary: Modulo ponte tra provvigioni agenti e RiBa
Home-page: https://github.com/OCA/l10n-italy
Author: Nextev Srl, Odoo Community Association (OCA)
Author-email: support@odoo-community.org
License: AGPL-3
Classifier: Programming Language :: Python
Classifier: Framework :: Odoo
Classifier: Framework :: Odoo :: 14.0
Classifier: License :: OSI Approved :: GNU Affero General Public License v3
Classifier: Development Status :: 3 - Alpha
Requires-Python: >=3.6
Requires-Dist: odoo14-addon-l10n-it-ricevute-bancarie
Requires-Dist: odoo14-addon-sale-commission-partial-settlement
Requires-Dist: odoo <14.1dev,>=14.0a
